ulid/__init__.py
ulid/base32.py
ulid/codec.py
ulid/consts.py
ulid/hints.py
ulid/py.typed
ulid/ulid.py
ulid_py-1.0.0.dist-info/LICENSE
ulid_py-1.0.0.dist-info/METADATA
ulid_py-1.0.0.dist-info/WHEEL
ulid_py-1.0.0.dist-info/top_level.txt
ulid_py-1.0.0.dist-info/RECORD
